[
  {
    "title": "BMW-M4 GT3",
    "category": "Car",
    "device": "Desktop",
    "author": "BMW",
    "res": "5120x2880",
    "size": "4.71 MB",
    "url": "https://raw.githubusercontent.com/ITZ-FBI/lumina-wallpapers/main/images/thumb_1781514508502.jpg",
    "tags": [
      "bmw",
      "car",
      "automobile"
    ],
    "colors": [
      "#1e293b",
      "#3b82f6",
      "#8b5cf6"
    ],
    "id": 1781514508502,
    "timestamp": 1781514508502,
    "fullUrl": "https://raw.githubusercontent.com/ITZ-FBI/lumina-wallpapers/main/images/full_1781514508502.jpg"
  }
]